HISTORY.rst
LICENSE.txt
MANIFEST.in
README.rst
setup.cfg
setup.py
test_schedule.py
micropython_schedule.egg-info/PKG-INFO
micropython_schedule.egg-info/SOURCES.txt
micropython_schedule.egg-info/dependency_links.txt
micropython_schedule.egg-info/requires.txt
micropython_schedule.egg-info/top_level.txt
schedule/__init__.py